vectorizer/__init__.py
vectorizer/vectorizer.py
hvectorizer-0.1.1.dist-info/METADATA
hvectorizer-0.1.1.dist-info/WHEEL
hvectorizer-0.1.1.dist-info/top_level.txt
hvectorizer-0.1.1.dist-info/RECORD
