Metadata-Version: 2.1
Name: hvectorizer
Version: 0.1.1
Summary: This package aims to facilitate natural languange processing
Home-page: http://example.com/mypackage
Author: Simean Hamado
Author-email: fatihamtech@gmail.com
Classifier: Programming Language :: Python :: 3
Requires-Python: >=3.6
